cce/__init__.py
cce/cli.py
cce/config.py
cce-0.2.3.dist-info/licenses/LICENSE
data_utils/SimAD_data_loader2.py
data_utils/__init__.py
evaluation/__init__.py
evaluation/analysis_metrics/__init__.py
evaluation/analysis_metrics/analysis_cce_hyperparam.py
evaluation/analysis_metrics/analysis_cce_latency.py
evaluation/analysis_metrics/analysis_latency.py
evaluation/analysis_metrics/analysis_plot_utils.py
evaluation/analysis_metrics/analysis_rank.py
evaluation/analysis_metrics/analysis_rank_real.py
evaluation/eval_metrics/__init__.py
evaluation/eval_metrics/eval_latency.py
evaluation/eval_metrics/eval_latency_baselines.py
evaluation/eval_metrics/eval_metric_real_model.py
evaluation/eval_metrics/eval_rank_utils.py
evaluation/eval_metrics/eval_utils.py
metrics/AUC.py
metrics/Matthews_correlation_coefficient.py
metrics/__init__.py
metrics/basic_metrics.py
metrics/combine_all_scores.py
metrics/customizable_f1_score.py
metrics/evaluate_utils.py
metrics/f1_series.py
metrics/fc_score.py
metrics/metrics.py
metrics/precision_at_k.py
metrics/affiliation/_affiliation_zone.py
metrics/affiliation/_integral_interval.py
metrics/affiliation/_single_ground_truth_event.py
metrics/affiliation/generics.py
metrics/affiliation/metrics.py
metrics/eTaPR_pkg/__init__.py
metrics/eTaPR_pkg/etapr.py
metrics/eTaPR_pkg/tapr.py
metrics/eTaPR_pkg/DataManage/File_IO.py
metrics/eTaPR_pkg/DataManage/Range.py
metrics/eTaPR_pkg/DataManage/Time_Plot.py
metrics/eTaPR_pkg/DataManage/__init__.py
metrics/pate/PATE_metric.py
metrics/pate/PATE_utils.py
metrics/pate/__init__.py
metrics/vus/metrics.py
metrics/vus/analysis/robustness_eval.py
metrics/vus/analysis/score_computation.py
metrics/vus/models/distance.py
metrics/vus/models/feature.py
metrics/vus/utils/metrics.py
metrics/vus/utils/slidingWindows.py
utils/__init__.py
utils/dataset.py
utils/model_wrapper.py
utils/slidingWindows.py
utils/stat_models.py
utils/torch_utility.py
utils/utility.py
cce-0.2.3.dist-info/METADATA
cce-0.2.3.dist-info/WHEEL
cce-0.2.3.dist-info/entry_points.txt
cce-0.2.3.dist-info/top_level.txt
cce-0.2.3.dist-info/RECORD
