Metadata-Version: 2.4
Name: cce
Version: 0.2.3
Summary: Confidence-Consistency Evaluation for Time Series Anomaly Detection
Home-page: https://github.com/EmorZz1G/CCE
Author: EmorZz1G
Author-email: EmorZz1G <csemor@mail.scut.edu.cn>
Maintainer: EmorZz1G
Maintainer-email: EmorZz1G <csemor@mail.scut.edu.cn>
License-Expression: MIT
Project-URL: Homepage, https://github.com/EmorZz1G/CCE
Project-URL: Documentation, https://github.com/EmorZz1G/CCE#readme
Project-URL: Repository, https://github.com/EmorZz1G/CCE.git
Project-URL: Issues, https://github.com/EmorZz1G/CCE/issues
Project-URL: Changelog, https://github.com/EmorZz1G/CCE/blob/main/CHANGELOG.md
Keywords: time-series,anomaly-detection,evaluation,metrics,machine-learning,confidence-consistency
Classifier: Development Status :: 4 - Beta
Classifier: Intended Audience :: Developers
Classifier: Intended Audience :: Science/Research
Classifier: Operating System :: OS Independent
Classifier: Programming Language :: Python :: 3
Classifier: Programming Language :: Python :: 3.8
Classifier: Programming Language :: Python :: 3.9
Classifier: Programming Language :: Python :: 3.10
Classifier: Programming Language :: Python :: 3.11
Classifier: Programming Language :: Python :: 3.12
Classifier: Topic :: Scientific/Engineering :: Artificial Intelligence
Classifier: Topic :: Scientific/Engineering :: Information Analysis
Classifier: Topic :: Software Development :: Libraries :: Python Modules
Requires-Python: >=3.8
License-File: LICENSE
Requires-Dist: torch>=1.8.0
Requires-Dist: numpy>=1.19.0
Requires-Dist: scipy>=1.7.0
Requires-Dist: scikit-learn>=1.0.0
Requires-Dist: pandas>=1.3.0
Requires-Dist: matplotlib>=3.3.0
Requires-Dist: seaborn>=0.11.0
Requires-Dist: tqdm>=4.60.0
Requires-Dist: pyyaml>=5.4.0
Requires-Dist: deprecated>=1.2.0
Provides-Extra: dev
Requires-Dist: pytest>=6.0; extra == "dev"
Requires-Dist: pytest-cov>=2.0; extra == "dev"
Requires-Dist: black>=21.0; extra == "dev"
Requires-Dist: flake8>=3.8; extra == "dev"
Requires-Dist: mypy>=0.800; extra == "dev"
Requires-Dist: pre-commit>=2.0; extra == "dev"
Provides-Extra: docs
Requires-Dist: sphinx>=4.0; extra == "docs"
Requires-Dist: sphinx-rtd-theme>=1.0; extra == "docs"
Requires-Dist: myst-parser>=0.15; extra == "docs"
Provides-Extra: jupyter
Requires-Dist: jupyter>=1.0.0; extra == "jupyter"
Requires-Dist: ipython>=7.0.0; extra == "jupyter"
Requires-Dist: plotly>=5.0.0; extra == "jupyter"
Requires-Dist: bokeh>=2.4.0; extra == "jupyter"
Requires-Dist: streamlit>=1.20.0; extra == "jupyter"
Provides-Extra: all
Requires-Dist: cce[dev,docs,jupyter]; extra == "all"
Dynamic: author
Dynamic: home-page
Dynamic: license-file
Dynamic: maintainer
Dynamic: requires-python
